splunksplwrapper/SearchUtil.py
splunksplwrapper/__init__.py
splunksplwrapper/app/__init__.py
splunksplwrapper/connector/__init__.py
splunksplwrapper/connector/base.py
splunksplwrapper/connector/httplib2_handler.py
splunksplwrapper/connector/rest.py
splunksplwrapper/connector/sdk.py
splunksplwrapper/exceptions/__init__.py
splunksplwrapper/exceptions/command_execution.py
splunksplwrapper/exceptions/confs.py
splunksplwrapper/exceptions/search.py
splunksplwrapper/exceptions/wait.py
splunksplwrapper/log/__init__.py
splunksplwrapper/log/logging.conf
splunksplwrapper/manager/__init__.py
splunksplwrapper/manager/confs/__init__.py
splunksplwrapper/manager/confs/conf.py
splunksplwrapper/manager/confs/rest/__init__.py
splunksplwrapper/manager/confs/rest/conf.py
splunksplwrapper/manager/confs/rest/stanza.py
splunksplwrapper/manager/confs/sdk/__init__.py
splunksplwrapper/manager/confs/sdk/conf.py
splunksplwrapper/manager/confs/sdk/stanza.py
splunksplwrapper/manager/confs/stanza.py
splunksplwrapper/manager/indexes/__init__.py
splunksplwrapper/manager/indexes/index.py
splunksplwrapper/manager/indexes/rest/__init__.py
splunksplwrapper/manager/indexes/rest/index.py
splunksplwrapper/manager/indexes/sdk/__init__.py
splunksplwrapper/manager/indexes/sdk/index.py
splunksplwrapper/manager/jobs/__init__.py
splunksplwrapper/manager/jobs/job.py
splunksplwrapper/manager/jobs/rest/__init__.py
splunksplwrapper/manager/jobs/rest/job.py
splunksplwrapper/manager/jobs/results.py
splunksplwrapper/manager/jobs/sdk/__init__.py
splunksplwrapper/manager/jobs/sdk/job.py
splunksplwrapper/manager/object.py
splunksplwrapper/manager/roles/__init__.py
splunksplwrapper/manager/roles/role.py
splunksplwrapper/manager/roles/sdk/__init__.py
splunksplwrapper/manager/roles/sdk/role.py
splunksplwrapper/manager/saved_searches/__init__.py
splunksplwrapper/manager/saved_searches/saved_search.py
splunksplwrapper/manager/saved_searches/sdk/__init__.py
splunksplwrapper/manager/saved_searches/sdk/saved_search.py
splunksplwrapper-1.1.4.dist-info/LICENSE
splunksplwrapper-1.1.4.dist-info/METADATA
splunksplwrapper-1.1.4.dist-info/WHEEL
splunksplwrapper-1.1.4.dist-info/RECORD
