Metadata-Version: 2.1
Name: splunksplwrapper
Version: 1.1.4
Summary: Package to interact with Splunk
License: Apache-2.0
Author: Splunk
Author-email: addonfactory@splunk.com
Requires-Python: >=3.7,<4.0
Classifier: License :: OSI Approved :: Apache Software License
Classifier: Programming Language :: Python :: 3
Classifier: Programming Language :: Python :: 3.7
Classifier: Programming Language :: Python :: 3.8
Classifier: Programming Language :: Python :: 3.9
Classifier: Programming Language :: Python :: 3.10
Classifier: Programming Language :: Python :: 3.11
Requires-Dist: defusedxml (>=0.7.1,<0.8.0)
Requires-Dist: httplib2 (>=0.20.0)
Requires-Dist: splunk-sdk (>=1.6.20)
